<?xml version="1.0" encoding="utf-8"?>
<AssemblyCandidate xmlns:xsd="http://www.w3.org/2001/XMLSchema" xmlns:xsi="http://www.w3.org/2001/XMLSchema-instance">
  <GenerationStatus />
  <performanceParams />
  <recipe />
  <designParameters />
  <activeRuleSetIndex>0</activeRuleSetIndex>
  <age>0</age>
  <Sequence>
    <Subassemblies>
      <SubAssembly Name="subasm-PumpAssembly - BackLid2-1.STL,PumpAssembly - Pump-1.STL,PumpAssembly - Ring-1.STL,PumpAssembly - Shaft-1.STL,PumpAssembly - Lid-1.STL,PumpAssembly - PumpExtention-2 InnerRing-1.STL,PumpAssembly - PumpExtention-2 ShaftThrough-1.STL,PumpAssembly - PumpExtention-2 Side-2.STL,PumpAssembly - PumpExtention-2 Pipe-1.STL,PumpAssembly - PumpExtention-2 Side-1.STL">
        <Mass>858395.4781600011</Mass>
        <Volume>858395.4781600011</Volume>
        <InternalStabilityInfo>
          <OverAllDOF>1</OverAllDOF>
          <OverAllTippingScore>58.8</OverAllTippingScore>
          <OverAllSlidingScore>0</OverAllSlidingScore>
          <MaxSingleDOF>1</MaxSingleDOF>
          <MinSingleTippingScore>9.8</MinSingleTippingScore>
          <MinSingleSlidingScore>0</MinSingleSlidingScore>
          <Totalsecore>0.06597222222222221</Totalsecore>
          <needfixture>false</needfixture>
        </InternalStabilityInfo>
        <Install>
          <Time>0.874979393882948</Time>
          <TimeSD>12.10455096043405</TimeSD>
          <Reference xsi:type="SubAssembly" Name="subasm-PumpAssembly - Pump-1.STL,PumpAssembly - Shaft-1.STL,PumpAssembly - Ring-1.STL,PumpAssembly - BackLid2-1.STL">
            <Mass>705269.88066547178</Mass>
            <Volume>705269.88066547178</Volume>
            <InternalStabilityInfo>
              <OverAllDOF>3.5</OverAllDOF>
              <OverAllTippingScore>9.8</OverAllTippingScore>
              <OverAllSlidingScore>0</OverAllSlidingScore>
              <MaxSingleDOF>3.5</MaxSingleDOF>
              <MinSingleTippingScore>9.8</MinSingleTippingScore>
              <MinSingleSlidingScore>0</MinSingleSlidingScore>
              <Totalsecore>0.19791666666666669</Totalsecore>
              <needfixture>false</needfixture>
            </InternalStabilityInfo>
            <Install>
              <Time>10.400817583456394</Time>
              <TimeSD>13.872192224446428</TimeSD>
              <Reference xsi:type="SubAssembly" Name="subasm-PumpAssembly - Shaft-1.STL,PumpAssembly - Pump-1.STL,PumpAssembly - Ring-1.STL">
                <Mass>672004.50597952865</Mass>
                <Volume>672004.50597952865</Volume>
                <InternalStabilityInfo>
                  <OverAllDOF>3.5</OverAllDOF>
                  <OverAllTippingScore>9.8</OverAllTippingScore>
                  <OverAllSlidingScore>0</OverAllSlidingScore>
                  <MaxSingleDOF>3.5</MaxSingleDOF>
                  <MinSingleTippingScore>9.8</MinSingleTippingScore>
                  <MinSingleSlidingScore>0</MinSingleSlidingScore>
                  <Totalsecore>0.16666666666666669</Totalsecore>
                  <needfixture>false</needfixture>
                </InternalStabilityInfo>
                <Install>
                  <Time>9.9721034563309789</Time>
                  <TimeSD>13.998904731687361</TimeSD>
                  <Reference xsi:type="SubAssembly" Name="subasm-PumpAssembly - Pump-1.STL,PumpAssembly - Shaft-1.STL">
                    <Mass>670494.28354808362</Mass>
                    <Volume>670494.28354808362</Volume>
                    <InternalStabilityInfo>
                      <OverAllDOF>3.5</OverAllDOF>
                      <OverAllTippingScore>9.8</OverAllTippingScore>
                      <OverAllSlidingScore>0</OverAllSlidingScore>
                      <MaxSingleDOF>3.5</MaxSingleDOF>
                      <MinSingleTippingScore>9.8</MinSingleTippingScore>
                      <MinSingleSlidingScore>0</MinSingleSlidingScore>
                      <Totalsecore>0.29166666666666669</Totalsecore>
                      <needfixture>false</needfixture>
                    </InternalStabilityInfo>
                    <Install>
                      <Time>1.0383985636905804</Time>
                      <TimeSD>12.949781727982373</TimeSD>
                      <Reference xsi:type="SubAssembly" Name="subasm-PumpAssembly - Pump-1.STL">
                        <Mass>513533.45727260364</Mass>
                        <Volume>513533.45727260364</Volume>
                        <InstallCharacter>Unknown</InstallCharacter>
                      </Reference>
                      <Moving xsi:type="SubAssembly" Name="subasm-PumpAssembly - Shaft-1.STL">
                        <Mass>156960.82627547998</Mass>
                        <Volume>156960.82627547998</Volume>
                        <InstallCharacter>Unknown</InstallCharacter>
                      </Moving>
                      <InstallDirection>
                        <double>0.0349</double>
                        <double>0.9988</double>
                        <double>0.0349</double>
                      </InstallDirection>
                      <InstallDistance>361.07669030399995</InstallDistance>
                      <InstallDirectionRotated>
                        <double>-0.24933924453822681</double>
                        <double>-0.93272174613254144</double>
                        <double>-0.26057157447536233</double>
                      </InstallDirectionRotated>
                    </Install>
                    <Secure>
                      <Time>0</Time>
                      <TimeSD>0</TimeSD>
                      <Fasteners />
                    </Secure>
                    <Rotate>
                      <Time>0</Time>
                      <TimeSD>0</TimeSD>
                    </Rotate>
                    <InstallCharacter>MovingIsInsideReference</InstallCharacter>
                  </Reference>
                  <Moving xsi:type="SubAssembly" Name="subasm-PumpAssembly - Ring-1.STL">
                    <Mass>1510.2224314450004</Mass>
                    <Volume>1510.2224314450004</Volume>
                    <InstallCharacter>Unknown</InstallCharacter>
                  </Moving>
                  <InstallDirection>
                    <double>-0.0697</double>
                    <double>0.9962</double>
                    <double>-0.0523</double>
                  </InstallDirection>
                  <InstallDistance>228.75144806899993</InstallDistance>
                  <InstallDirectionRotated>
                    <double>-0.377441453328398</double>
                    <double>-0.028935816810225765</double>
                    <double>-0.92558548379653849</double>
                  </InstallDirectionRotated>
                </Install>
                <Secure>
                  <Time>0</Time>
                  <TimeSD>0</TimeSD>
                  <Fasteners />
                </Secure>
                <Rotate>
                  <Time>0</Time>
                  <TimeSD>0</TimeSD>
                </Rotate>
                <InstallCharacter>MovingIsInsideReference</InstallCharacter>
              </Reference>
              <Moving xsi:type="SubAssembly" Name="subasm-PumpAssembly - BackLid2-1.STL">
                <Mass>33265.374685943112</Mass>
                <Volume>33265.374685943112</Volume>
                <InstallCharacter>Unknown</InstallCharacter>
              </Moving>
              <InstallDirection>
                <double>0</double>
                <double>0</double>
                <double>1</double>
              </InstallDirection>
              <InstallDistance>263.766934</InstallDistance>
              <InstallDirectionRotated>
                <double>-0.066368470025132117</double>
                <double>-0.9977936432759118</double>
                <double>-0.0017526051197926384</double>
              </InstallDirectionRotated>
            </Install>
            <Secure>
              <Time>0</Time>
              <TimeSD>0</TimeSD>
              <Fasteners>
                <Fastener>
                  <Time>0</Time>
                  <TimeSD>0</TimeSD>
                  <InstallDirection>
                    <double>-0</double>
                    <double>-0</double>
                    <double>-1</double>
                  </InstallDirection>
                  <InstallDistance>186.883462</InstallDistance>
                  <InstallDirectionRotated>
                    <double>0.066368470025132117</double>
                    <double>0.9977936432759118</double>
                    <double>0.0017526051197926384</double>
                  </InstallDirectionRotated>
                  <RemovalDirection>0</RemovalDirection>
                  <Certainty>0</Certainty>
                  <Tool>HexWrench</Tool>
                  <ToolSize>0</ToolSize>
                  <Diameter>10.015863786841985</Diameter>
                  <OverallLength>0</OverallLength>
                  <EngagedLength>0</EngagedLength>
                  <AccessCylinderRadius>0</AccessCylinderRadius>
                  <FastenerType>Bolt</FastenerType>
                  <NumberOfThreads>0</NumberOfThreads>
                  <Nuts />
                  <Washer />
                  <PartsLockedByFastener />
                </Fastener>
                <Fastener>
                  <Time>0</Time>
                  <TimeSD>0</TimeSD>
                  <InstallDirection>
                    <double>-0</double>
                    <double>-0</double>
                    <double>-1</double>
                  </InstallDirection>
                  <InstallDistance>186.883462</InstallDistance>
                  <InstallDirectionRotated>
                    <double>0.066368470025132117</double>
                    <double>0.9977936432759118</double>
                    <double>0.0017526051197926384</double>
                  </InstallDirectionRotated>
                  <RemovalDirection>0</RemovalDirection>
                  <Certainty>0</Certainty>
                  <Tool>HexWrench</Tool>
                  <ToolSize>0</ToolSize>
                  <Diameter>10.015863786926548</Diameter>
                  <OverallLength>0</OverallLength>
                  <EngagedLength>0</EngagedLength>
                  <AccessCylinderRadius>0</AccessCylinderRadius>
                  <FastenerType>Bolt</FastenerType>
                  <NumberOfThreads>0</NumberOfThreads>
                  <Nuts />
                  <Washer />
                  <PartsLockedByFastener />
                </Fastener>
              </Fasteners>
            </Secure>
            <Rotate>
              <Time>0</Time>
              <TimeSD>0</TimeSD>
            </Rotate>
            <InstallCharacter>MovingIsOnOutsideOfReference</InstallCharacter>
          </Reference>
          <Moving xsi:type="SubAssembly" Name="subasm-PumpAssembly - PumpExtention-2 InnerRing-1.STL,PumpAssembly - PumpExtention-2 ShaftThrough-1.STL,PumpAssembly - PumpExtention-2 Side-2.STL,PumpAssembly - PumpExtention-2 Pipe-1.STL,PumpAssembly - Lid-1.STL,PumpAssembly - PumpExtention-2 Side-1.STL">
            <Mass>153125.5974945293</Mass>
            <Volume>153125.5974945293</Volume>
            <InternalStabilityInfo>
              <OverAllDOF>0</OverAllDOF>
              <OverAllTippingScore>19.6</OverAllTippingScore>
              <OverAllSlidingScore>0</OverAllSlidingScore>
              <MaxSingleDOF>0</MaxSingleDOF>
              <MinSingleTippingScore>9.8</MinSingleTippingScore>
              <MinSingleSlidingScore>0</MinSingleSlidingScore>
              <Totalsecore>0.03125</Totalsecore>
              <needfixture>false</needfixture>
            </InternalStabilityInfo>
            <Install>
              <Time>0.6609453365944894</Time>
              <TimeSD>12.999755037408482</TimeSD>
              <Reference xsi:type="SubAssembly" Name="subasm-PumpAssembly - PumpExtention-2 ShaftThrough-1.STL,PumpAssembly - PumpExtention-2 Side-2.STL,PumpAssembly - PumpExtention-2 InnerRing-1.STL,PumpAssembly - PumpExtention-2 Pipe-1.STL">
                <Mass>83466.6563981134</Mass>
                <Volume>83466.6563981134</Volume>
                <InternalStabilityInfo>
                  <OverAllDOF>4</OverAllDOF>
                  <OverAllTippingScore>19.6</OverAllTippingScore>
                  <OverAllSlidingScore>0</OverAllSlidingScore>
                  <MaxSingleDOF>2</MaxSingleDOF>
                  <MinSingleTippingScore>9.8</MinSingleTippingScore>
                  <MinSingleSlidingScore>0</MinSingleSlidingScore>
                  <Totalsecore>0.098958333333333315</Totalsecore>
                  <needfixture>false</needfixture>
                </InternalStabilityInfo>
                <Install>
                  <Time>1.6365712445478144</Time>
                  <TimeSD>13.604205332417262</TimeSD>
                  <Reference xsi:type="SubAssembly" Name="subasm-PumpAssembly - PumpExtention-2 ShaftThrough-1.STL,PumpAssembly - PumpExtention-2 Side-2.STL">
                    <Mass>48271.938127422378</Mass>
                    <Volume>48271.938127422378</Volume>
                    <InternalStabilityInfo>
                      <OverAllDOF>3.5</OverAllDOF>
                      <OverAllTippingScore>9.8</OverAllTippingScore>
                      <OverAllSlidingScore>0</OverAllSlidingScore>
                      <MaxSingleDOF>3.5</MaxSingleDOF>
                      <MinSingleTippingScore>9.8</MinSingleTippingScore>
                      <MinSingleSlidingScore>0</MinSingleSlidingScore>
                      <Totalsecore>0.29166666666666669</Totalsecore>
                      <needfixture>false</needfixture>
                    </InternalStabilityInfo>
                    <Install>
                      <Time>2.2237292762661851</Time>
                      <TimeSD>13.695769658544194</TimeSD>
                      <Reference xsi:type="SubAssembly" Name="subasm-PumpAssembly - PumpExtention-2 ShaftThrough-1.STL">
                        <Mass>36758.261797917548</Mass>
                        <Volume>36758.261797917548</Volume>
                        <InstallCharacter>Unknown</InstallCharacter>
                      </Reference>
                      <Moving xsi:type="SubAssembly" Name="subasm-PumpAssembly - PumpExtention-2 Side-2.STL">
                        <Mass>11513.676329504828</Mass>
                        <Volume>11513.676329504828</Volume>
                        <InstallCharacter>Unknown</InstallCharacter>
                      </Moving>
                      <InstallDirection>
                        <double>0.9986</double>
                        <double>0</double>
                        <double>0.0523</double>
                      </InstallDirection>
                      <InstallDistance>150.074199757</InstallDistance>
                      <InstallDirectionRotated>
                        <double>0.9986</double>
                        <double>0.013535596419724549</double>
                        <double>-0.050518092101368393</double>
                      </InstallDirectionRotated>
                    </Install>
                    <Secure>
                      <Time>0</Time>
                      <TimeSD>0</TimeSD>
                      <Fasteners />
                    </Secure>
                    <Rotate>
                      <Time>0</Time>
                      <TimeSD>0</TimeSD>
                    </Rotate>
                    <InstallCharacter>MovingReferenceSimiliar</InstallCharacter>
                  </Reference>
                  <Moving xsi:type="SubAssembly" Name="subasm-PumpAssembly - PumpExtention-2 Pipe-1.STL,PumpAssembly - PumpExtention-2 InnerRing-1.STL">
                    <Mass>35194.718270691017</Mass>
                    <Volume>35194.718270691017</Volume>
                    <InternalStabilityInfo>
                      <OverAllDOF>3.5</OverAllDOF>
                      <OverAllTippingScore>9.8</OverAllTippingScore>
                      <OverAllSlidingScore>0</OverAllSlidingScore>
                      <MaxSingleDOF>3.5</MaxSingleDOF>
                      <MinSingleTippingScore>9.8</MinSingleTippingScore>
                      <MinSingleSlidingScore>0</MinSingleSlidingScore>
                      <Totalsecore>0.29166666666666669</Totalsecore>
                      <needfixture>false</needfixture>
                    </InternalStabilityInfo>
                    <Install>
                      <Time>2.4624973213728478</Time>
                      <TimeSD>13.758468939910287</TimeSD>
                      <Reference xsi:type="SubAssembly" Name="subasm-PumpAssembly - PumpExtention-2 Pipe-1.STL">
                        <Mass>23429.125261533027</Mass>
                        <Volume>23429.125261533027</Volume>
                        <InstallCharacter>Unknown</InstallCharacter>
                      </Reference>
                      <Moving xsi:type="SubAssembly" Name="subasm-PumpAssembly - PumpExtention-2 InnerRing-1.STL">
                        <Mass>11765.593009157988</Mass>
                        <Volume>11765.593009157988</Volume>
                        <InstallCharacter>Unknown</InstallCharacter>
                      </Moving>
                      <InstallDirection>
                        <double>-0.9986</double>
                        <double>-0</double>
                        <double>-0.0523</double>
                      </InstallDirection>
                      <InstallDistance>182.84162424149986</InstallDistance>
                      <InstallDirectionRotated>
                        <double>-0.9986</double>
                        <double>0.0030432646025521765</double>
                        <double>0.052211383246940059</double>
                      </InstallDirectionRotated>
                    </Install>
                    <Secure>
                      <Time>0</Time>
                      <TimeSD>0</TimeSD>
                      <Fasteners />
                    </Secure>
                    <Rotate>
                      <Time>0</Time>
                      <TimeSD>0</TimeSD>
                    </Rotate>
                    <InstallCharacter>MovingIsInsideReference</InstallCharacter>
                  </Moving>
                  <InstallDirection>
                    <double>0.9994</double>
                    <double>0</double>
                    <double>0.0349</double>
                  </InstallDirection>
                  <InstallDistance>320.6837330615</InstallDistance>
                  <InstallDirectionRotated>
                    <double>0.9994</double>
                    <double>-0.0098797439633007446</double>
                    <double>0.033472386518137942</double>
                  </InstallDirectionRotated>
                </Install>
                <Secure>
                  <Time>0</Time>
                  <TimeSD>0</TimeSD>
                  <Fasteners />
                </Secure>
                <Rotate>
                  <Time>0</Time>
                  <TimeSD>0</TimeSD>
                </Rotate>
                <InstallCharacter>MovingReferenceSimiliar</InstallCharacter>
              </Reference>
              <Moving xsi:type="SubAssembly" Name="subasm-PumpAssembly - Lid-1.STL,PumpAssembly - PumpExtention-2 Side-1.STL">
                <Mass>69658.9410964159</Mass>
                <Volume>69658.9410964159</Volume>
                <InternalStabilityInfo>
                  <OverAllDOF>3.5</OverAllDOF>
                  <OverAllTippingScore>9.8</OverAllTippingScore>
                  <OverAllSlidingScore>0</OverAllSlidingScore>
                  <MaxSingleDOF>3.5</MaxSingleDOF>
                  <MinSingleTippingScore>9.8</MinSingleTippingScore>
                  <MinSingleSlidingScore>0</MinSingleSlidingScore>
                  <Totalsecore>0.29166666666666669</Totalsecore>
                  <needfixture>false</needfixture>
                </InternalStabilityInfo>
                <Install>
                  <Time>3.9711267229636591</Time>
                  <TimeSD>13.806530226097543</TimeSD>
                  <Reference xsi:type="SubAssembly" Name="subasm-PumpAssembly - Lid-1.STL">
                    <Mass>58145.329444492272</Mass>
                    <Volume>58145.329444492272</Volume>
                    <InstallCharacter>Unknown</InstallCharacter>
                  </Reference>
                  <Moving xsi:type="SubAssembly" Name="subasm-PumpAssembly - PumpExtention-2 Side-1.STL">
                    <Mass>11513.611651923633</Mass>
                    <Volume>11513.611651923633</Volume>
                    <InstallCharacter>Unknown</InstallCharacter>
                  </Moving>
                  <InstallDirection>
                    <double>-0.9994</double>
                    <double>-0</double>
                    <double>-0.0349</double>
                  </InstallDirection>
                  <InstallDistance>120.98140000000001</InstallDistance>
                  <InstallDirectionRotated>
                    <double>0.10942720453515298</double>
                    <double>0</double>
                    <double>-0.99400405276217141</double>
                  </InstallDirectionRotated>
                </Install>
                <Secure>
                  <Time>0</Time>
                  <TimeSD>0</TimeSD>
                  <Fasteners />
                </Secure>
                <Rotate>
                  <Time>0</Time>
                  <TimeSD>0</TimeSD>
                </Rotate>
                <InstallCharacter>MovingReferenceSimiliar</InstallCharacter>
              </Moving>
              <InstallDirection>
                <double>0.9986</double>
                <double>0</double>
                <double>0.0523</double>
              </InstallDirection>
              <InstallDistance>336.96439975699991</InstallDistance>
              <InstallDirectionRotated>
                <double>-0.33469042905511287</double>
                <double>-0.19443143198492707</double>
                <double>-0.92201734525723289</double>
              </InstallDirectionRotated>
            </Install>
            <Secure>
              <Time>0</Time>
              <TimeSD>0</TimeSD>
              <Fasteners>
                <Fastener>
                  <Time>0</Time>
                  <TimeSD>0</TimeSD>
                  <InstallDirection>
                    <double>0.0349</double>
                    <double>0.9992</double>
                    <double>0.0175</double>
                  </InstallDirection>
                  <InstallDistance>159.761117985</InstallDistance>
                  <InstallDirectionRotated>
                    <double>0.58864803798136556</double>
                    <double>0.70213382392644663</double>
                    <double>-0.400532746075916</double>
                  </InstallDirectionRotated>
                  <RemovalDirection>4645</RemovalDirection>
                  <Certainty>0</Certainty>
                  <Tool>HexWrench</Tool>
                  <ToolSize>0</ToolSize>
                  <Diameter>17.219194667941835</Diameter>
                  <OverallLength>0</OverallLength>
                  <EngagedLength>0</EngagedLength>
                  <AccessCylinderRadius>0</AccessCylinderRadius>
                  <FastenerType>Bolt</FastenerType>
                  <NumberOfThreads>0</NumberOfThreads>
                  <Nuts />
                  <Washer />
                </Fastener>
                <Fastener>
                  <Time>0</Time>
                  <TimeSD>0</TimeSD>
                  <InstallDirection>
                    <double>0.0349</double>
                    <double>0.9992</double>
                    <double>0.0175</double>
                  </InstallDirection>
                  <InstallDistance>155.88828866000006</InstallDistance>
                  <InstallDirectionRotated>
                    <double>0.58864803798136556</double>
                    <double>0.70213382392644663</double>
                    <double>-0.400532746075916</double>
                  </InstallDirectionRotated>
                  <RemovalDirection>4645</RemovalDirection>
                  <Certainty>0</Certainty>
                  <Tool>HexWrench</Tool>
                  <ToolSize>0</ToolSize>
                  <Diameter>17.219195014141906</Diameter>
                  <OverallLength>0</OverallLength>
                  <EngagedLength>0</EngagedLength>
                  <AccessCylinderRadius>0</AccessCylinderRadius>
                  <FastenerType>Bolt</FastenerType>
                  <NumberOfThreads>0</NumberOfThreads>
                  <Nuts />
                  <Washer />
                </Fastener>
              </Fasteners>
            </Secure>
            <Rotate>
              <Time>0</Time>
              <TimeSD>0</TimeSD>
            </Rotate>
            <InstallCharacter>MovingReferenceSimiliar</InstallCharacter>
          </Moving>
          <InstallDirection>
            <double>0.0349</double>
            <double>0.9988</double>
            <double>0.0349</double>
          </InstallDirection>
          <InstallDistance>404.4728327283</InstallDistance>
          <InstallDirectionRotated>
            <double>-0.27321959916824551</double>
            <double>0.0514631716418047</double>
            <double>-0.9605935938756357</double>
          </InstallDirectionRotated>
        </Install>
        <Secure>
          <Time>0</Time>
          <TimeSD>0</TimeSD>
          <Fasteners>
            <Fastener>
              <Time>0</Time>
              <TimeSD>0</TimeSD>
              <InstallDirection>
                <double>0.0166</double>
                <double>0.9509</double>
                <double>0.309</double>
              </InstallDirection>
              <InstallDistance>320.65444684299996</InstallDistance>
              <InstallDirectionRotated>
                <double>-0.25758795812704094</double>
                <double>0.32521863840824861</double>
                <double>-0.90986188570564219</double>
              </InstallDirectionRotated>
              <RemovalDirection>4199</RemovalDirection>
              <Certainty>0</Certainty>
              <Tool>HexWrench</Tool>
              <ToolSize>0</ToolSize>
              <Diameter>3.7000615648566013</Diameter>
              <OverallLength>0</OverallLength>
              <EngagedLength>0</EngagedLength>
              <AccessCylinderRadius>0</AccessCylinderRadius>
              <FastenerType>Bolt</FastenerType>
              <NumberOfThreads>0</NumberOfThreads>
              <Nuts />
              <Washer />
              <PartsLockedByFastener />
            </Fastener>
            <Fastener>
              <Time>0</Time>
              <TimeSD>0</TimeSD>
              <InstallDirection>
                <double>0.0166</double>
                <double>0.9509</double>
                <double>0.309</double>
              </InstallDirection>
              <InstallDistance>325.35758128299994</InstallDistance>
              <InstallDirectionRotated>
                <double>-0.25758795812704094</double>
                <double>0.32521863840824861</double>
                <double>-0.90986188570564219</double>
              </InstallDirectionRotated>
              <RemovalDirection>4199</RemovalDirection>
              <Certainty>0</Certainty>
              <Tool>HexWrench</Tool>
              <ToolSize>0</ToolSize>
              <Diameter>3.7000882961747936</Diameter>
              <OverallLength>0</OverallLength>
              <EngagedLength>0</EngagedLength>
              <AccessCylinderRadius>0</AccessCylinderRadius>
              <FastenerType>Bolt</FastenerType>
              <NumberOfThreads>0</NumberOfThreads>
              <Nuts />
              <Washer />
              <PartsLockedByFastener />
            </Fastener>
            <Fastener>
              <Time>0</Time>
              <TimeSD>0</TimeSD>
              <InstallDirection>
                <double>0.0166</double>
                <double>0.9509</double>
                <double>0.309</double>
              </InstallDirection>
              <InstallDistance>324.27768820299991</InstallDistance>
              <InstallDirectionRotated>
                <double>-0.25758795812704094</double>
                <double>0.32521863840824861</double>
                <double>-0.90986188570564219</double>
              </InstallDirectionRotated>
              <RemovalDirection>4199</RemovalDirection>
              <Certainty>0</Certainty>
              <Tool>HexWrench</Tool>
              <ToolSize>0</ToolSize>
              <Diameter>3.7000427596874887</Diameter>
              <OverallLength>0</OverallLength>
              <EngagedLength>0</EngagedLength>
              <AccessCylinderRadius>0</AccessCylinderRadius>
              <FastenerType>Bolt</FastenerType>
              <NumberOfThreads>0</NumberOfThreads>
              <Nuts />
              <Washer />
              <PartsLockedByFastener />
            </Fastener>
            <Fastener>
              <Time>0</Time>
              <TimeSD>0</TimeSD>
              <InstallDirection>
                <double>0.0166</double>
                <double>0.9509</double>
                <double>0.309</double>
              </InstallDirection>
              <InstallDistance>334.1048715629999</InstallDistance>
              <InstallDirectionRotated>
                <double>-0.25758795812704094</double>
                <double>0.32521863840824861</double>
                <double>-0.90986188570564219</double>
              </InstallDirectionRotated>
              <RemovalDirection>4199</RemovalDirection>
              <Certainty>0</Certainty>
              <Tool>HexWrench</Tool>
              <ToolSize>0</ToolSize>
              <Diameter>3.7000373242575564</Diameter>
              <OverallLength>0</OverallLength>
              <EngagedLength>0</EngagedLength>
              <AccessCylinderRadius>0</AccessCylinderRadius>
              <FastenerType>Bolt</FastenerType>
              <NumberOfThreads>0</NumberOfThreads>
              <Nuts />
              <Washer />
              <PartsLockedByFastener />
            </Fastener>
            <Fastener>
              <Time>0</Time>
              <TimeSD>0</TimeSD>
              <InstallDirection>
                <double>0.0166</double>
                <double>0.9509</double>
                <double>0.309</double>
              </InstallDirection>
              <InstallDistance>335.632071563</InstallDistance>
              <InstallDirectionRotated>
                <double>-0.25758795812704094</double>
                <double>0.32521863840824861</double>
                <double>-0.90986188570564219</double>
              </InstallDirectionRotated>
              <RemovalDirection>4199</RemovalDirection>
              <Certainty>0</Certainty>
              <Tool>HexWrench</Tool>
              <ToolSize>0</ToolSize>
              <Diameter>3.7000518730821264</Diameter>
              <OverallLength>0</OverallLength>
              <EngagedLength>0</EngagedLength>
              <AccessCylinderRadius>0</AccessCylinderRadius>
              <FastenerType>Bolt</FastenerType>
              <NumberOfThreads>0</NumberOfThreads>
              <Nuts />
              <Washer />
              <PartsLockedByFastener />
            </Fastener>
            <Fastener>
              <Time>0</Time>
              <TimeSD>0</TimeSD>
              <InstallDirection>
                <double>0.0166</double>
                <double>0.9509</double>
                <double>0.309</double>
              </InstallDirection>
              <InstallDistance>333.098885983</InstallDistance>
              <InstallDirectionRotated>
                <double>-0.25758795812704094</double>
                <double>0.32521863840824861</double>
                <double>-0.90986188570564219</double>
              </InstallDirectionRotated>
              <RemovalDirection>4199</RemovalDirection>
              <Certainty>0</Certainty>
              <Tool>HexWrench</Tool>
              <ToolSize>0</ToolSize>
              <Diameter>3.7000310816646165</Diameter>
              <OverallLength>0</OverallLength>
              <EngagedLength>0</EngagedLength>
              <AccessCylinderRadius>0</AccessCylinderRadius>
              <FastenerType>Bolt</FastenerType>
              <NumberOfThreads>0</NumberOfThreads>
              <Nuts />
              <Washer />
              <PartsLockedByFastener />
            </Fastener>
            <Fastener>
              <Time>0</Time>
              <TimeSD>0</TimeSD>
              <InstallDirection>
                <double>0.0166</double>
                <double>0.9509</double>
                <double>0.309</double>
              </InstallDirection>
              <InstallDistance>336.72211807299993</InstallDistance>
              <InstallDirectionRotated>
                <double>-0.25758795812704094</double>
                <double>0.32521863840824861</double>
                <double>-0.90986188570564219</double>
              </InstallDirectionRotated>
              <RemovalDirection>4199</RemovalDirection>
              <Certainty>0</Certainty>
              <Tool>HexWrench</Tool>
              <ToolSize>0</ToolSize>
              <Diameter>3.7000084640209874</Diameter>
              <OverallLength>0</OverallLength>
              <EngagedLength>0</EngagedLength>
              <AccessCylinderRadius>0</AccessCylinderRadius>
              <FastenerType>Bolt</FastenerType>
              <NumberOfThreads>0</NumberOfThreads>
              <Nuts />
              <Washer />
              <PartsLockedByFastener />
            </Fastener>
            <Fastener>
              <Time>0</Time>
              <TimeSD>0</TimeSD>
              <InstallDirection>
                <double>0.0166</double>
                <double>0.9509</double>
                <double>0.309</double>
              </InstallDirection>
              <InstallDistance>332.01899290299997</InstallDistance>
              <InstallDirectionRotated>
                <double>-0.25758795812704094</double>
                <double>0.32521863840824861</double>
                <double>-0.90986188570564219</double>
              </InstallDirectionRotated>
              <RemovalDirection>4199</RemovalDirection>
              <Certainty>0</Certainty>
              <Tool>HexWrench</Tool>
              <ToolSize>0</ToolSize>
              <Diameter>3.7000625719337559</Diameter>
              <OverallLength>0</OverallLength>
              <EngagedLength>0</EngagedLength>
              <AccessCylinderRadius>0</AccessCylinderRadius>
              <FastenerType>Bolt</FastenerType>
              <NumberOfThreads>0</NumberOfThreads>
              <Nuts />
              <Washer />
              <PartsLockedByFastener />
            </Fastener>
            <Fastener>
              <Time>0</Time>
              <TimeSD>0</TimeSD>
              <InstallDirection>
                <double>0.0166</double>
                <double>0.9509</double>
                <double>0.309</double>
              </InstallDirection>
              <InstallDistance>353.35539909299996</InstallDistance>
              <InstallDirectionRotated>
                <double>-0.25758795812704094</double>
                <double>0.32521863840824861</double>
                <double>-0.90986188570564219</double>
              </InstallDirectionRotated>
              <RemovalDirection>4199</RemovalDirection>
              <Certainty>0</Certainty>
              <Tool>HexWrench</Tool>
              <ToolSize>0</ToolSize>
              <Diameter>4.0027867399038461</Diameter>
              <OverallLength>0</OverallLength>
              <EngagedLength>0</EngagedLength>
              <AccessCylinderRadius>0</AccessCylinderRadius>
              <FastenerType>Bolt</FastenerType>
              <NumberOfThreads>0</NumberOfThreads>
              <Nuts />
              <Washer />
              <PartsLockedByFastener>
                <int>1</int>
                <int>2</int>
                <int>6</int>
              </PartsLockedByFastener>
            </Fastener>
            <Fastener>
              <Time>0</Time>
              <TimeSD>0</TimeSD>
              <InstallDirection>
                <double>0.0166</double>
                <double>0.9509</double>
                <double>0.309</double>
              </InstallDirection>
              <InstallDistance>368.80632507299993</InstallDistance>
              <InstallDirectionRotated>
                <double>-0.25758795812704094</double>
                <double>0.32521863840824861</double>
                <double>-0.90986188570564219</double>
              </InstallDirectionRotated>
              <RemovalDirection>4199</RemovalDirection>
              <Certainty>0</Certainty>
              <Tool>HexWrench</Tool>
              <ToolSize>0</ToolSize>
              <Diameter>4.0028209482256933</Diameter>
              <OverallLength>0</OverallLength>
              <EngagedLength>0</EngagedLength>
              <AccessCylinderRadius>0</AccessCylinderRadius>
              <FastenerType>Bolt</FastenerType>
              <NumberOfThreads>0</NumberOfThreads>
              <Nuts />
              <Washer />
              <PartsLockedByFastener>
                <int>1</int>
                <int>2</int>
                <int>6</int>
              </PartsLockedByFastener>
            </Fastener>
            <Fastener>
              <Time>0</Time>
              <TimeSD>0</TimeSD>
              <InstallDirection>
                <double>0.0166</double>
                <double>0.9509</double>
                <double>0.309</double>
              </InstallDirection>
              <InstallDistance>351.811599093</InstallDistance>
              <InstallDirectionRotated>
                <double>-0.25758795812704094</double>
                <double>0.32521863840824861</double>
                <double>-0.90986188570564219</double>
              </InstallDirectionRotated>
              <RemovalDirection>4199</RemovalDirection>
              <Certainty>0</Certainty>
              <Tool>HexWrench</Tool>
              <ToolSize>0</ToolSize>
              <Diameter>4.0028088776564745</Diameter>
              <OverallLength>0</OverallLength>
              <EngagedLength>0</EngagedLength>
              <AccessCylinderRadius>0</AccessCylinderRadius>
              <FastenerType>Bolt</FastenerType>
              <NumberOfThreads>0</NumberOfThreads>
              <Nuts />
              <Washer />
              <PartsLockedByFastener>
                <int>1</int>
                <int>2</int>
                <int>7</int>
              </PartsLockedByFastener>
            </Fastener>
            <Fastener>
              <Time>0</Time>
              <TimeSD>0</TimeSD>
              <InstallDirection>
                <double>0.0166</double>
                <double>0.9509</double>
                <double>0.309</double>
              </InstallDirection>
              <InstallDistance>367.261592913</InstallDistance>
              <InstallDirectionRotated>
                <double>-0.25758795812704094</double>
                <double>0.32521863840824861</double>
                <double>-0.90986188570564219</double>
              </InstallDirectionRotated>
              <RemovalDirection>4199</RemovalDirection>
              <Certainty>0</Certainty>
              <Tool>HexWrench</Tool>
              <ToolSize>0</ToolSize>
              <Diameter>4.002808917625992</Diameter>
              <OverallLength>0</OverallLength>
              <EngagedLength>0</EngagedLength>
              <AccessCylinderRadius>0</AccessCylinderRadius>
              <FastenerType>Bolt</FastenerType>
              <NumberOfThreads>0</NumberOfThreads>
              <Nuts />
              <Washer />
              <PartsLockedByFastener>
                <int>1</int>
                <int>2</int>
                <int>7</int>
              </PartsLockedByFastener>
            </Fastener>
          </Fasteners>
        </Secure>
        <Rotate>
          <Time>0</Time>
          <TimeSD>0</TimeSD>
        </Rotate>
        <InstallCharacter>MovingIsOnOutsideOfReference</InstallCharacter>
      </SubAssembly>
    </Subassemblies>
  </Sequence>
  <TimeScore>NaN</TimeScore>
  <AccessibilityScore>NaN</AccessibilityScore>
  <StabilityScore>NaN</StabilityScore>
</AssemblyCandidate>